meris_checker/__init__.py
meris_checker/checker.py
meris_checker-1.1.0.dist-info/entry_points.txt
meris_checker-1.1.0.dist-info/WHEEL
meris_checker-1.1.0.dist-info/METADATA
meris_checker-1.1.0.dist-info/RECORD
